pyproject.toml
setup.py
pxlDB/__init__.py
pxlDB.egg-info/PKG-INFO
pxlDB.egg-info/SOURCES.txt
pxlDB.egg-info/dependency_links.txt
pxlDB.egg-info/top_level.txt